README.md
setup.py
log_everywhere/__init__.py
log_everywhere/logger.py
log_everywhere.egg-info/PKG-INFO
log_everywhere.egg-info/SOURCES.txt
log_everywhere.egg-info/dependency_links.txt
log_everywhere.egg-info/top_level.txt